<?xml version="1.0" encoding="UTF-8"?>
<objects serializationModel="Studio.01.10.00">
    <object class="ParameterPreset" id="{d1e4bb1f-97d7-4d4b-80d0-f2fa51fd3d3b}">
        <property name="name">
            <value>Distance</value>
        </property>
        <relationship name="folder">
            <destination>{b6c7ccc4-e5b5-4c6e-bdf9-9f53cce8f2a3}</destination>
        </relationship>
        <relationship name="parameter">
            <destination>{19772cf7-fcaf-42ef-8b6b-478133844d2f}</destination>
        </relationship>
    </object>
    <object class="GameParameter" id="{19772cf7-fcaf-42ef-8b6b-478133844d2f}">
        <property name="parameterType">
            <value>1</value>
        </property>
        <property name="maximum">
            <value>1500</value>
        </property>
        <property name="initialValue">
            <value>0</value>
        </property>
        <property name="isExposedRecursively">
            <value>false</value>
        </property>
    </object>
</objects>
